sbr_model/__init__.py
sbr_model/model.py
sbr_model-0.2.1.dist-info/licenses/LICENSE
sbr_model-0.2.1.dist-info/METADATA
sbr_model-0.2.1.dist-info/WHEEL
sbr_model-0.2.1.dist-info/top_level.txt
sbr_model-0.2.1.dist-info/RECORD
