Metadata-Version: 2.4
Name: sbr-model
Version: 0.2.1
Summary: Un regresor de Machine Learning que implementa un ensamblaje de Stacking con modelos de Boosting.
Author-email: Pablo Eduardo Chavez Mercado <pablo.chavez1992@gmail.com>
License: MIT License
Keywords: stacking,boosting,regressor,ensemble,xgboost,machine-learning
Classifier: Development Status :: 3 - Alpha
Classifier: License :: OSI Approved :: MIT License
Classifier: Programming Language :: Python :: 3
Classifier: Topic :: Scientific/Engineering :: Artificial Intelligence
Requires-Python: >=3.8
License-File: LICENSE
Requires-Dist: numpy
Requires-Dist: scikit-learn
Requires-Dist: xgboost
Requires-Dist: lightgbm
Requires-Dist: catboost
Requires-Dist: pandas
Dynamic: license-file
